agent_ledger_sdk/__init__.py
agent_ledger_sdk/client.py
agent_ledger_sdk/py.typed
agent_ledger_sdk-0.0.6.dist-info/METADATA
agent_ledger_sdk-0.0.6.dist-info/WHEEL
agent_ledger_sdk-0.0.6.dist-info/RECORD
