Metadata-Version: 2.4
Name: agent-ledger-sdk
Version: 0.0.6
Summary: Official Python client for the Agent Ledger API
Project-URL: Homepage, https://agent-ledger.thabo.xyz
Project-URL: Source, https://github.com/furahadamien/agent-ledger
Author: Agent Ledger
License: MIT
Keywords: agents,ai,instrumentation,observability,sdk
Classifier: Development Status :: 3 - Alpha
Classifier: Intended Audience :: Developers
Classifier: License :: OSI Approved :: MIT License
Classifier: Programming Language :: Python
Classifier: Programming Language :: Python :: 3
Classifier: Programming Language :: Python :: 3.9
Classifier: Programming Language :: Python :: 3.10
Classifier: Programming Language :: Python :: 3.11
Classifier: Programming Language :: Python :: 3.12
Classifier: Programming Language :: Python :: 3.13
Classifier: Typing :: Typed
Requires-Python: >=3.9
Requires-Dist: httpx<0.28,>=0.26
Requires-Dist: typing-extensions>=4.7.0
Provides-Extra: dev
Requires-Dist: pytest>=8.0; extra == 'dev'
